sertipy/__init__.py
sertipy/auth.py
sertipy/client.py
sertipy/exceptions.py
sertipy-1.1.0.dist-info/LICENSE.md
sertipy-1.1.0.dist-info/METADATA
sertipy-1.1.0.dist-info/WHEEL
sertipy-1.1.0.dist-info/top_level.txt
sertipy-1.1.0.dist-info/RECORD
