Metadata-Version: 2.1
Name: sertipy
Version: 1.1.0
Summary: Python library for the Sertiva Web API
Home-page: https://github.com/btechpt/sertipy
Author: Boer Technology
Author-email: dev@btech.id
License: UNKNOWN
Project-URL: Bug Tracker, https://github.com/btechpt/sertipy/issues
Platform: UNKNOWN
Classifier: Programming Language :: Python :: 3
Classifier: License :: OSI Approved :: MIT License
Classifier: Operating System :: OS Independent
Requires-Python: >=3.6
License-File: LICENSE.md
Requires-Dist: requests
